few_shot_clustering/__init__.py
few_shot_clustering/active_clustering.py
few_shot_clustering/dataloaders.py
few_shot_clustering/eval_utils.py
few_shot_clustering/experiment_utils.py
few_shot_clustering/utils.py
few_shot_clustering/wrappers.py
few_shot_clustering/active_semi_supervised_clustering/__init__.py
few_shot_clustering/active_semi_supervised_clustering/setup.py
few_shot_clustering/active_semi_supervised_clustering/active_semi_clustering/__init__.py
few_shot_clustering/active_semi_supervised_clustering/active_semi_clustering/exceptions.py
few_shot_clustering/active_semi_supervised_clustering/active_semi_clustering/farthest_first_traversal.py
few_shot_clustering/active_semi_supervised_clustering/active_semi_clustering/active/__init__.py
few_shot_clustering/active_semi_supervised_clustering/active_semi_clustering/active/pairwise_constraints/__init__.py
few_shot_clustering/active_semi_supervised_clustering/active_semi_clustering/active/pairwise_constraints/distance_based_selector.py
few_shot_clustering/active_semi_supervised_clustering/active_semi_clustering/active/pairwise_constraints/example_oracle.py
few_shot_clustering/active_semi_supervised_clustering/active_semi_clustering/active/pairwise_constraints/explore_consolidate.py
few_shot_clustering/active_semi_supervised_clustering/active_semi_clustering/active/pairwise_constraints/gpt3_comparative_oracle.py
few_shot_clustering/active_semi_supervised_clustering/active_semi_clustering/active/pairwise_constraints/gpt3_pc_oracle.py
few_shot_clustering/active_semi_supervised_clustering/active_semi_clustering/active/pairwise_constraints/helpers.py
few_shot_clustering/active_semi_supervised_clustering/active_semi_clustering/active/pairwise_constraints/label_based_selector.py
few_shot_clustering/active_semi_supervised_clustering/active_semi_clustering/active/pairwise_constraints/min_max.py
few_shot_clustering/active_semi_supervised_clustering/active_semi_clustering/active/pairwise_constraints/min_max_finetune.py
few_shot_clustering-0.0.3.dist-info/METADATA
few_shot_clustering-0.0.3.dist-info/WHEEL
few_shot_clustering-0.0.3.dist-info/licenses/LICENSE
few_shot_clustering-0.0.3.dist-info/RECORD
