Metadata-Version: 2.1
Name: few_shot_clustering
Version: 0.0.3
Summary: A library for efficient semi-supervised clustering with large language models.
Author-email: Vijay Viswanathan <vijayv@andrew.cmu.edu>
License-File: LICENSE
Classifier: Programming Language :: Python :: 3.7
Requires-Python: >=3.7
Requires-Dist: datasets
Requires-Dist: gensim
Requires-Dist: instructorembedding
Requires-Dist: jsonlines
Requires-Dist: metric-learn
Requires-Dist: nlpaug
Requires-Dist: numpy
Requires-Dist: openai
Requires-Dist: ortools
Requires-Dist: scikit-learn
Requires-Dist: scipy
Requires-Dist: sentence-transformers
Requires-Dist: tensorboardx
Requires-Dist: tqdm
